commonroad_all/__init__.py
commonroad_all-0.1.0.dist-info/METADATA
commonroad_all-0.1.0.dist-info/WHEEL
commonroad_all-0.1.0.dist-info/RECORD
