Metadata-Version: 2.1
Name: commonroad-all
Version: 0.1.0
Summary: Meta-Package for installing all CommonRoad Tools
License: GPL-3.0-or-later
Keywords: autonomous,automated,vehicles,driving,motion,planning,simulation,map,scenario
Author: Cyber-Physical Systems Group, Technical University of Munich
Author-email: commonroad@lists.lrz.de
Requires-Python: >=3.8,<3.11
Classifier: License :: OSI Approved :: GNU General Public License v3 or later (GPLv3+)
Classifier: Operating System :: POSIX :: Linux
Classifier: Programming Language :: Python :: 3
Classifier: Programming Language :: Python :: 3.8
Classifier: Programming Language :: Python :: 3.9
Classifier: Programming Language :: Python :: 3.10
Requires-Dist: commonroad-crime (==0.3.0)
Requires-Dist: commonroad-dataset-converter (==2023.2)
Requires-Dist: commonroad-drivability-checker (==2023.1)
Requires-Dist: commonroad-io (==2023.3)
Requires-Dist: commonroad-reach (==2023.1.1)
Requires-Dist: commonroad-route-planner (==2022.3)
Requires-Dist: commonroad-scenario-designer (==0.8.0)
Requires-Dist: commonroad-vehicle-models (==3.0.2)
Requires-Dist: sumocr (==2023.2)
